[
    {
        "filter": [
            {
                "header": "From",
                "match": "buchungsbestaetigung@bahn.de",
                "type": "Email"
            },
            {
                "match": "uic:0080",
                "property": "reservationFor.provider.identifier",
                "type": "JsonLd"
            },
            {
                "match": "vdv:6260",
                "property": "reservationFor.provider.identifier",
                "type": "JsonLd"
            }
        ],
        "function": "parsePdf",
        "script": "deutschebahn.js",
        "type": "Pdf"
    },
    {
        "filter": [
            {
                "header": "From",
                "match": "UNITTEST-buchungsbestaetigung@bahn.de",
                "type": "Email"
            }
        ],
        "function": "parseText",
        "script": "deutschebahn.js",
        "type": "Text"
    },
    {
        "filter": [
            {
                "header": "From",
                "match": "buchungsbestaetigung@bahn.de",
                "type": "Email"
            }
        ],
        "function": "parseCancellation",
        "script": "deutschebahn.js",
        "type": "Html"
    }
]
