[
    {
        "@context": "http://schema.org",
        "@type": "FlightReservation",
        "reservationFor": {
            "@type": "Flight",
            "airline": {
                "@type": "Airline",
                "iataCode": "BT",
                "name": "Air Baltic"
            },
            "arrivalAirport": {
                "@type": "Airport",
                "iataCode": "RIX",
                "name": "Riga"
            },
            "arrivalTime": "2017-11-05T11:35:00",
            "departureAirport": {
                "@type": "Airport",
                "iataCode": "TXL",
                "name": "Tegel"
            },
            "departureDay": "2017-11-05",
            "departureTime": "2017-11-05T08:55:00",
            "flightNumber": "212"
        },
        "reservationNumber": "ABCDEF"
    },
    {
        "@context": "http://schema.org",
        "@type": "FlightReservation",
        "reservationFor": {
            "@type": "Flight",
            "airline": {
                "@type": "Airline",
                "iataCode": "BT",
                "name": "Air Baltic"
            },
            "arrivalAirport": {
                "@type": "Airport",
                "iataCode": "TXL",
                "name": "Tegel"
            },
            "arrivalTime": "2017-11-10T08:20:00",
            "departureAirport": {
                "@type": "Airport",
                "iataCode": "RIX",
                "name": "Riga"
            },
            "departureDay": "2017-11-10",
            "departureTime": "2017-11-10T07:35:00",
            "flightNumber": "211"
        },
        "reservationNumber": "ABCDEF"
    }
]
